<?xml version="1.0" encoding="UTF-8"?>
<objects serializationModel="Studio.02.02.00">
	<object class="AudioFile" id="{6182b7f8-50af-4ed8-9915-d2c07b83c5b3}">
		<property name="assetPath">
			<value>SnakeHiss_MonoEqued.wav</value>
		</property>
		<property name="frequencyInKHz">
			<value>44.0999985</value>
		</property>
		<property name="channelCount">
			<value>1</value>
		</property>
		<property name="length">
			<value>1.7678684807256235</value>
		</property>
		<relationship name="masterAssetFolder">
			<destination>{2444f894-6aed-4d47-8969-18c09831076a}</destination>
		</relationship>
	</object>
</objects>
