<?xml version="1.0" encoding="UTF-8"?>
<objects serializationModel="Studio.02.02.00">
	<object class="AudioFile" id="{bc30887c-9899-4383-96b3-4a11a8c38f7c}">
		<property name="assetPath">
			<value>Mushroom Game Sounds/MusicParts/Mv2_Synth2.mp3</value>
		</property>
		<property name="isStreaming">
			<value>true</value>
		</property>
		<property name="frequencyInKHz">
			<value>44.0999985</value>
		</property>
		<property name="channelCount">
			<value>2</value>
		</property>
		<property name="length">
			<value>14.497959183673469</value>
		</property>
		<relationship name="masterAssetFolder">
			<destination>{2444f894-6aed-4d47-8969-18c09831076a}</destination>
		</relationship>
	</object>
</objects>
